sympy2jax/__init__.py
sympy2jax/sympy_module.py
sympy2jax-0.0.7.dist-info/METADATA
sympy2jax-0.0.7.dist-info/WHEEL
sympy2jax-0.0.7.dist-info/licenses/LICENSE
sympy2jax-0.0.7.dist-info/RECORD
