Metadata-Version: 2.4
Name: sympy2jax
Version: 0.0.7
Summary: Turn SymPy expressions into trainable JAX expressions.
Project-URL: repository, https://github.com/google/sympy2jax
Author-email: Patrick Kidger <contact@kidger.site>
License: 
License-File: LICENSE
Keywords: equinox,jax,sympy
Classifier: Development Status :: 3 - Alpha
Classifier: Intended Audience :: Science/Research
Classifier: License :: OSI Approved :: Apache Software License
Classifier: Natural Language :: English
Classifier: Programming Language :: Python :: 3
Classifier: Topic :: Scientific/Engineering :: Artificial Intelligence
Classifier: Topic :: Scientific/Engineering :: Mathematics
Requires-Python: ~=3.9
Requires-Dist: equinox>=0.5.3
Requires-Dist: jax>=0.3.4
Requires-Dist: sympy>=1.7.1
